reader/__init__.py
reader/__main__.py
reader/config.cfg
reader/feed.py
reader/viewer.py
prove_test_runner-1.1.0.dist-info/LICENSE
prove_test_runner-1.1.0.dist-info/METADATA
prove_test_runner-1.1.0.dist-info/WHEEL
prove_test_runner-1.1.0.dist-info/entry_points.txt
prove_test_runner-1.1.0.dist-info/top_level.txt
prove_test_runner-1.1.0.dist-info/RECORD
