Metadata-Version: 2.1
Name: prove-test-runner
Version: 1.1.0
Summary: Read the latest Real Python tutorials
Home-page: https://github.com
Author: Real Python
Author-email: joelbarrantes@gamil.com
License: MIT
Platform: UNKNOWN
Classifier: License :: OSI Approved :: MIT License
Classifier: Programming Language :: Python
Classifier: Programming Language :: Python :: 3
License-File: LICENSE
Requires-Dist: feedparser
Requires-Dist: html2text
